kudio-1.2.0.0.dist-info/METADATA
kudio-1.2.0.0.dist-info/WHEEL
kudio-1.2.0.0.dist-info/top_level.txt
kudio-1.2.0.0.dist-info/LICENSE
kudio-1.2.0.0.dist-info/RECORD
kudio/version.cpython-38-x86_64-linux-gnu.so
kudio/_config.cpython-38-x86_64-linux-gnu.so
kudio/__init__.py
kudio/kudio/version.py
kudio/kudio/_config.py
kudio/kudio/__init__.py
kudio/kudio/util/conv.py
kudio/kudio/util/colors.py
kudio/kudio/util/check.py
kudio/kudio/util/tools.py
kudio/kudio/util/visual.py
kudio/kudio/util/others.py
kudio/kudio/util/__init__.py
kudio/kudio/_enh/trad.py
kudio/kudio/_enh/__init__.py
kudio/kudio/core/stream.py
kudio/kudio/core/manager.py
kudio/kudio/core/buffer.py
kudio/kudio/core/synth.py
kudio/kudio/core/io.py
kudio/kudio/core/__init__.py
kudio/kudio/core/evaluator.py
kudio/kudio/core/feature.py
kudio/util/others.cpython-38-x86_64-linux-gnu.so
kudio/util/colors.py
kudio/util/visual.cpython-38-x86_64-linux-gnu.so
kudio/util/tools.cpython-38-x86_64-linux-gnu.so
kudio/util/conv.cpython-38-x86_64-linux-gnu.so
kudio/util/__init__.py
kudio/util/check.cpython-38-x86_64-linux-gnu.so
kudio/_enh/trad.cpython-38-x86_64-linux-gnu.so
kudio/_enh/__init__.py
kudio/core/evaluator.cpython-38-x86_64-linux-gnu.so
kudio/core/manager.cpython-38-x86_64-linux-gnu.so
kudio/core/synth.cpython-38-x86_64-linux-gnu.so
kudio/core/stream.cpython-38-x86_64-linux-gnu.so
kudio/core/feature.cpython-38-x86_64-linux-gnu.so
kudio/core/io.cpython-38-x86_64-linux-gnu.so
kudio/core/__init__.py
kudio/core/buffer.cpython-38-x86_64-linux-gnu.so
